biasedurn-0.0.2.dist-info/top_level.txt
biasedurn-0.0.2.dist-info/RECORD
biasedurn-0.0.2.dist-info/METADATA
biasedurn-0.0.2.dist-info/WHEEL
biasedurn/cpp_src/_core.cpython-34m.so
biasedurn/cpp_src/core.py
biasedurn/cpp_src/__init__.py
